ironbyte/__init__.py
ironbyte/executor.py
ironbyte/obfuscator.py
ironbyte/utils.py
ironbyte-1.0.0.dist-info/METADATA
ironbyte-1.0.0.dist-info/WHEEL
ironbyte-1.0.0.dist-info/top_level.txt
ironbyte-1.0.0.dist-info/RECORD
